pyRockBlock/__init__.py
pyRockBlock/pyRockBlock.py
pyRockBlock-1.0.6.dist-info/LICENSE
pyRockBlock-1.0.6.dist-info/METADATA
pyRockBlock-1.0.6.dist-info/WHEEL
pyRockBlock-1.0.6.dist-info/top_level.txt
pyRockBlock-1.0.6.dist-info/RECORD
