Metadata-Version: 2.1
Name: pyRockBlock
Version: 1.0.6
Summary: The definitive RockBLOCK Python 3 package.
Home-page: https://github.com/cathedral30/pyRockBlock
Author: Henry Cooper
Author-email: cooper.henry30@gmail.com
Project-URL: Documentation, https://cathedral30.github.io/pyRockBlock/
License-File: LICENSE
